Workbook

Sheet Invoice
B1: ='Coghlan Settings'!E27&IF('Coghlan Settings'!E28<>""," - " &'Coghlan Settings'!E28,"") -> Coghlan Sydney Pty Ltd | H1: Tax Invoice
B2: ='Coghlan Settings'!E29 -> ABN 53003527526 | G2: Date : | H2: ='Coghlan Settings'!B6 -> 46146
B3: ='Coghlan Settings'!E30 -> PO Box 6890 | G3: Inv # : | H3: ='Coghlan Settings'!B7 -> DOK50347
B4: ='Coghlan Settings'!E31 -> Wetherill Park NSW 2164 | G4: Period End : | H4: ='Coghlan Settings'!B8 -> 46143
B5: ='Coghlan Settings'!E32 -> Australia
D8: Description | F8: Quantity | G8: Unit Price | H8: Total
A9: To: | B9: ='Coghlan Settings'!B27 -> Dock & Bay PTY LTD
B10: =IF('Coghlan Settings'!B28 = "","",'Coghlan Settings'!B28) -> Ben Muller | D10: Support of e-Quik (weekly) | F10: 1 | G10: =SUMIF('Coghlan Settings'!J:J,"4.1",'Coghlan Settings'!M:M) -> 136.47 | H10: =ROUNDUP(F10*G10,2) -> 136.47
B11: =IF('Coghlan Settings'!B29 = "","",'Coghlan Settings'!B29) -> PO Box 8006 | D11: Storage (weekly)
B12: =IF('Coghlan Settings'!B30 = "","",'Coghlan Settings'!B30) | E12: Number of Pallets | G12: =SUMIF('Coghlan Settings'!J:J,"1.1",'Coghlan Settings'!M:M) -> 4.62 | H12: =ROUNDUP(F12*G12,2) -> 0
B13: ='Coghlan Settings'!B31&" "&'Coghlan Settings'!B32&" "&'Coghlan Settings'!B33 -> Tumbi Umbi NSW 2261 | E13: Number of In Pallet Racking Shelves | G13: =SUMIF('Coghlan Settings'!J:J,"1.2",'Coghlan Settings'!M:M) -> 5.72 | H13: =ROUNDUP(F13*G13,2) -> 0
B14: =IF('Coghlan Settings'!B34 = "","",'Coghlan Settings'!B34) -> Australia | E14: Number of Small Item Shelves | G14: =SUMIF('Coghlan Settings'!J:J,"1.3",'Coghlan Settings'!M:M) -> 3.53 | H14: =ROUNDUP(F14*G14,2) -> 0
B15: =IF('Coghlan Settings'!B35 = "","",'Coghlan Settings'!B35) -> ben@dockandbay.com | E15: Number of Small Item Shelf - 1/2 height | G15: =SUMIF('Coghlan Settings'!J:J,"1.4",'Coghlan Settings'!M:M) -> 2.11 | H15: =ROUNDUP(F15*G15,2) -> 0
B16: =IF('Coghlan Settings'!B36 = "","",'Coghlan Settings'!B36) | E16: Number of Small Item Tray | G16: =SUMIF('Coghlan Settings'!J:J,"1.5",'Coghlan Settings'!M:M) -> 0.12 | H16: =ROUNDUP(F16*G16,2) -> 0
B17: =IF('Coghlan Settings'!B37 = "","",'Coghlan Settings'!B37) | D17: Goods Into Store (see attached) | H17: ='Goods Into Store'!$L$8 -> 0
D18: Order Processing (see attached)
E19: Fulfilment | H19: ='Order Processing'!$AB$9 -> 820.8
E20: Postage & Freight | H20: ='Order Processing'!$AC$9 -> 1971.1
E21: Packaging | H21: ='Order Processing'!$AD$9 -> 60.18
A22: Payment Methods | D22: Returns | F22: 1 | G22: =SUMIF('Coghlan Settings'!J:J,"6.1",'Coghlan Settings'!M:M) -> 4.64 | H22: =ROUNDUP(F22*G22,2) -> 4.64
B23: by EFT: | D23: Other Requests (see attached) | H23: =SUMIF('Other Requests'!$N$10:$N$2000,">=0") -> 1647.52
B24: ="Account Name: "&'Coghlan Settings'!H26 -> Account Name: Coghlan Sydney Pty Ltd | D24: Other Credits (see attached) | H24: =SUMIF('Other Requests'!$N$10:$N$2000,"<0") -> 0
B25: ="BSB: "&'Coghlan Settings'!H28 -> BSB: 062000 SWIFT: CTBAAU2S | D25: =IF('Coghlan Settings'!B48="Y",TEXT('Coghlan Settings'!B49,"0.00%")&" "&'Coghlan Settings'!B50,IF('Coghlan Settings'!B48="V",'Coghlan Settings'!B50,"")) | H25: =IF('Coghlan Settings'!B48="Y",ROUND('Coghlan Settings'!B49*-1*SUM(H8:H24),2),IF('Coghlan Settings'!B48="V",IF('Order Processing'!H2>'Coghlan Settings'!B53*1,ROUND('Coghlan Settings'!B54*-1*SUM(H8:H24),2),IF('Order Processing'!H2>'Coghlan Settings'!B55*1,ROUND('Coghlan Settings'!B56*-1*SUM(H8:H24),2),IF('Order Processing'!H2>'Coghlan Settings'!B57*1,ROUND('Coghlan Settings'!B58*-1*SUM(H8:H24),2),IF('Order Processing'!H2>'Coghlan Settings'!B59*1,ROUND('Coghlan Settings'!B60*-1*SUM(H8:H24),2),0)))),""))
B26: ="Account Number: "&'Coghlan Settings'!H29 -> Account Number: 21176183
B27: ="Payment Reference: "&'Coghlan Settings'!B26 -> Payment Reference: DOK | G27: Total Amount (excl GST) : | H27: =+SUM(H8:H26) -> 4640.71
B28: Email Remittance to ar@coghlan.com.au | F28: GST : | G28: =+'Coghlan Settings'!E33*1 -> 0.1 | H28: =ROUND(H27*G28,2) -> 464.07
G29: Total Amount (incl GST) AUD : | H29: =+SUM(H27:H28) -> 5104.78
B31: by Credit Card: | H31: ='Coghlan Settings'!B39 -> Payment Terms: Strictly 7 Days Net
B32: Please contact dee.habib@coghlan.com.au for details. | G32: Your next CPI increase is due : | H32: ='Coghlan Settings'!B38 -> 46241

Sheet Goods Into Store
A1: Goods Into Store | E1: Quoted Rates : | F1: =SUMIF('Coghlan Settings'!J:J,"2.1",'Coghlan Settings'!M:M) -> 10.37 | G1: Basic Charge then add
A2: =Invoice!$G$3 & Invoice!$H$3 -> Inv # : DOK50347 | F2: =SUMIF('Coghlan Settings'!J:J,"2.2.1",'Coghlan Settings'!M:M) -> 0 | G2: Per Product Type Received then add
A3: =Invoice!$G$4&TEXT(Invoice!$H$4,"dd mmm yy") -> Period End : 01 May 26 | F3: =SUMIF('Coghlan Settings'!J:J,"2.2.2",'Coghlan Settings'!M:M) -> 0 | G3: Per Item Received then add
F4: =SUMIF('Coghlan Settings'!J:J,"2.3",'Coghlan Settings'!M:M) -> 9.75 | G4: Per Standard Pallet (Single Product) or
F5: =SUMIF('Coghlan Settings'!J:J,"2.4",'Coghlan Settings'!M:M) -> 1.19 | G5: Per Carton (Single Product) or
F6: =SUMIF('Coghlan Settings'!J:J,"2.5",'Coghlan Settings'!M:M) -> 56.72 | G6: Mixed or Unstructured Deliveries - per hour
F7: =IF(SUMIF('Coghlan Settings'!J:J,"2.6",'Coghlan Settings'!M:M)>=1,"N","") | G7: Apply to Returns Goods Received Advice
K8: Total ($): | L8: =SUM(L11:L1048576) -> 0
A10: GRA ID | B10: GRA / RET | C10: Date | D10: # Line Items | E10: # Units of Stock | F10: Single Cartons | G10: Mixed Cartons | H10: Single Pallets | I10: Mixed Pallets | J10: # Minutes - Labour | K10: Container | L10: Total ($)

Sheet Order Processing
A1: Order Processing | F1: Quoted Rates : | G1: Unit $ | H1: Quantity | I1: Description
A2: =Invoice!G3 & Invoice!H3 -> Inv # : DOK50347 | G2: =SUMIF('Coghlan Settings'!J:J,"5.1",'Coghlan Settings'!M:M) -> 2.43 | H2: =SUM(C11:C1048576) -> 180 | I2: Price per Order Processed then add
A3: =Invoice!G4&TEXT(Invoice!H4,"dd mmm yy") -> Period End : 01 May 26 | G3: =SUMIF('Coghlan Settings'!J:J,"5.2",'Coghlan Settings'!M:M) -> 0.31 | H3: =SUM(D11:D1048576) -> 412 | I3: Lines on Order then add
G4: =SUMIF('Coghlan Settings'!J:J,"5.3",'Coghlan Settings'!M:M) -> 0.47 | H4: =SUM(E11:E1048576) -> 544 | I4: Items on Order then add
G5: =SUMIF('Coghlan Settings'!J:J,"5.4.1",'Coghlan Settings'!M:M) -> 0 | H5: =SUM(O11:O1048576) -> 181 | I5: Per Carton Despatched
G6: =SUMIF('Coghlan Settings'!J:J,"5.4.2",'Coghlan Settings'!M:M) -> 0 | H6: =SUM(J11:J1048576) -> 201.792 | I6: Per kilogram Despatched
G7: =SUMIF('Coghlan Settings'!J:J,"5.5",'Coghlan Settings'!M:M) -> 0 | H7: =COUNTA(N12:N1048576) -> 2 | I7: Address Correction (when required)
G8: =SUMIF('Coghlan Settings'!J:J,"5.7",'Coghlan Settings'!M:M) -> 0 | H8: =COUNTA(T12:T1048576) -> 0 | I8: Despatch Communication - Email (optional)
G9: =SUMIF('Coghlan Settings'!J:J,"5.8",'Coghlan Settings'!M:M) -> 0 | H9: =COUNTA(U12:U1048576) -> 0 | I9: Despatch Communication - SMS (optional) | AA9: Total ($): | AB9: =SUM(AB12:AB1048576) -> 820.8 | AC9: =SUM(AC12:AC1048576) -> 1971.1 | AD9: =SUM(AD12:AD1048576) -> 60.18
A11: TrxID | B11: Customer Ref | C11: Orders | D11: Lines | E11: Items | F11: Suburb | G11: Postcode | H11: Country | I11: Carrier | J11: Weight | L11: Time Stamp | M11: Packaging | N11: Address Correction | O11: No of Boxes | P11: Layout | Q11: Insurance | R11: Surcharge/Discount ($) | S11: Consignment No | T11: Email | V11: Items | W11: Zone | X11: Warehouse Hrs | Y11: Clerical Hrs | Z11: IT Hrs | AA11: Quoted Carrier ($) | AB11: Fulfilment Cost ($) | AC11: Carrier Cost ($) | AD11: Packaging Cost ($)
A13: 133099 | B13: AU-136731 | C13: 1 | D13: 1 | E13: 1 | F13: CAINTA | G13: 1900 | H13: PHILIPPINES | I13: 131 | J13: 1.2 | L13: 46141 | M13: @650966961404; | O13: 1 | P13: 10 | Q13: 0 | R13: 0 | S13: @LH416728089AU; | V13: @5061011624116@(..4116)Dock & Bay Picnic Blanket - Cand@1; | W13: 5 | AB13: 3.21 | AC13: 43.59 | AD13: 0.28
A14: 133343 | B14: AU-136975 | C14: 1 | D14: 3 | E14: 3 | F14: BLACKWATER | G14: 4717 | H14: AUSTRALIA | I14: 155 | J14: 0.863 | L14: 46143 | M14: @6943389500713; | O14: 1 | P14: 2 | Q14: 0 | R14: 0 | S14: @AXL6280878; | V14: @5061011625588@(..5588)Dock & Bay Hair Wrap - Hot Tropi@1;@5061011623867@(..3867)Dock & Bay Small Waterproof Dry@1;@5061011623591@(..3591)Dock & Bay Quick Dry Towel - Sun@1; | W14: Q3 | AB14: 4.77 | AC14: 20.68 | AD14: 0.81
A15: 133354 | B15: AU-136986 | C15: 1 | D15: 1 | E15: 1 | F15: MACLEOD | G15: 3085 | H15: AUSTRALIA | I15: 155 | J15: 0.547 | L15: 46140 | M15: @650966961381; | O15: 1 | P15: 2 | Q15: 0 | R15: 0 | S15: @AXL6284337; | V15: @5061011621436@(..1436)Dock & Bay Quick Dry Towel - San@1; | W15: V0 | AB15: 3.21 | AC15: 8.6 | AD15: 0.28
A16: 133355 | B16: AU-136987 | C16: 1 | D16: 10 | E16: 10 | F16: WARRAGUL | G16: 3820 | H16: AUSTRALIA | I16: 155 | J16: 2.726 | L16: 46140 | M16: @14; | O16: 1 | P16: 2 | Q16: 0 | R16: 0 | S16: @AXL6281952; | V16: @5061011626509@(..6509)Component Product@1;@5061011625908@(..5908)Component Product@1;@5061011626097@(..6097)Component Product@1;@5061011625632@(..5632)Component Product@1;@5061011625892@(..5892)Component Product@1;@5061011625793@(..5793)Dock & Bay Tea Towel - Kiss The@1;@5061011625885@(..5885)Dock & Bay Tea Towel - Very Appe@1;@5061011625779@(..5779)Dock & Bay Tea Towel - Cucumber@1;@5061011625755@(..5755)Dock & Bay Tea Towel - Pink Grap@1;@5061011624154@(..4154)Dock & Bay Picnic Blanket - Marg@1; | W16: V2 | AB16: 10.23 | AC16: 22.3 | AD16: 1.04
A17: 133356 | B17: AU-136988 | C17: 1 | D17: 1 | E17: 1 | F17: BRABHAM | G17: 6055 | H17: AUSTRALIA | I17: 155 | J17: 1.69 | L17: 46140 | M17: @650966961404; | O17: 1 | P17: 2 | Q17: 0 | R17: 0 | S17: @AXL6139767; | V17: @5061011624208@(..4208)Dock & Bay Picnic Blanket - Marg@1; | W17: W0 | AB17: 3.21 | AC17: 15.52 | AD17: 0.28
A18: 133357 | B18: AU-136989 | C18: 1 | D18: 3 | E18: 3 | F18: WOLLONGBAR | G18: 2477 | H18: AUSTRALIA | I18: 155 | J18: 0.642 | L18: 46140 | M18: @650966961398; | O18: 1 | P18: 2 | Q18: 0 | R18: 0 | S18: @AXL6251651; | V18: @5061011623874@(..3874)Dock & Bay Kids Beach Towel - Ka@1;@5061011628619@(..8619)Dock & Bay Tea Towel - Strawberr@1;@5061011628626@(..8626)Dock & Bay Tea Towel - Apple Tar@1; | W18: N2 | AB18: 4.77 | AC18: 13.77 | AD18: 0.28
A19: 133358 | B19: AU-136990 | C19: 1 | D19: 1 | E19: 1 | F19: POINT COOK | G19: 3030 | H19: AUSTRALIA | I19: 155 | J19: 0.271 | L19: 46140 | M19: @650966961381; | O19: 1 | P19: 2 | Q19: 0 | R19: 0 | S19: @AXL6139720; | V19: @5061011628442@(..8442)Dock & Bay Hair Wrap - Cherry Bo@1; | W19: V0 | AB19: 3.21 | AC19: 6.93 | AD19: 0.28
A20: 133359 | B20: AU-136991 | C20: 1 | D20: 1 | E20: 1 | F20: ST KILDA EAST | G20: 3183 | H20: AUSTRALIA | I20: 155 | J20: 1.17 | L20: 46140 | M20: @650966961404; | O20: 1 | P20: 2 | Q20: 0 | R20: 0 | S20: @AXL6285068; | V20: @5061011624130@(..4130)Dock & Bay Picnic Blanket - Stri@1; | W20: V0 | AB20: 3.21 | AC20: 9.27 | AD20: 0.28
A21: 133360 | B21: AU-136992 | C21: 1 | D21: 6 | E21: 12 | F21: CANNON VALLEY | G21: 4800 | H21: AUSTRALIA | I21: 155 | J21: 5.152 | L21: 46140 | M21: @14; | O21: 1 | P21: 2 | Q21: 0 | R21: 0 | S21: @AXL6244840; | V21: @5060668830963@(..0963)Component Product@2;@5060668833407@(..3407)Component Product@2;@5060668833414@(..3414)Component Product@2;@5060668830949@(..0949)Component Product@2;@5060668830918@(..0918)Component Product@2;@5060668830932@(..0932)Component Product@2; | W21: Q3 | AB21: 9.93 | AC21: 41.79 | AD21: 1.04
A22: 133361 | B22: AU-136993 | C22: 1 | D22: 1 | E22: 1 | F22: YERONGA | G22: 4104 | H22: AUSTRALIA | I22: 55 | J22: 0.45 | L22: 46140 | M22: @650966961381; | O22: 1 | P22: 2 | Q22: 0 | R22: 0 | S22: @AXL6285941; | V22: @5060668833407@(..3407)Dock & Bay Quick Dry Towel - Mal@1; | W22: Q0 | AB22: 3.21 | AC22: 6.93 | AD22: 0.28
A23: 133362 | B23: AU-136575A | C23: 1 | D23: 1 | E23: 1 | F23: WOOLLOONGABBA | G23: 4102 | H23: AUSTRALIA | I23: 155 | J23: 0.2 | L23: 46140 | M23: @650966961381; | O23: 1 | P23: 2 | Q23: 0 | R23: 0 | S23: @AXL6244841; | V23: @5060668837375@(..7375)Dock & Bay Foldaway Tote Bags -@1; | W23: Q0 | AB23: 3.21 | AC23: 6.93 | AD23: 0.28
A24: 133363 | B24: AU-136994 | C24: 1 | D24: 1 | E24: 1 | F24: PASCOE VALE SOUTH | G24: 3044 | H24: AUSTRALIA | I24: 155 | J24: 0.489 | L24: 46140 | M24: @650966961381; | O24: 1 | P24: 2 | Q24: 0 | R24: 0 | S24: @AXL6284518; | V24: @5061011623416@(..3416)Dock & Bay Quick Dry Towel - Gre@1; | W24: V0 | AB24: 3.21 | AC24: 6.93 | AD24: 0.28
A25: 133364 | B25: AU-136995 | C25: 1 | D25: 4 | E25: 4 | F25: MERRYLANDS | G25: 2160 | H25: AUSTRALIA | I25: 155 | J25: 1.224 | L25: 46140 | M25: @650966961398; | O25: 1 | P25: 2 | Q25: 0 | R25: 0 | S25: @AXL6284216; | V25: @5061011626257@(..6257)Dock & Bay Quick Dry Towel - Oce@1;@5061011625199@(..5199)Dock & Bay Quick Dry Towel - Hot@1;@5061011624215@(..4215)Dock & Bay Foldaway Tote Bags -@1;@5061011623225@(..3225)Dock & Bay Hair Wrap - Miami Sor@1; | W25: N0 | AB25: 5.55 | AC25: 5.96 | AD25: 0.28
... A60: 133399 | B60: AU-137029 | C60: 1 | D60: 1 | E60: 1 | F60: BOMADERRY | G60: 2541 | H60: AUSTRALIA | I60: 155 | J60: 0.55 | L60: 46140 | M60: @650966961381; | O60: 1 | P60: 2 | Q60: 0 | R60: 0 | S60: @AXL6285122; | V60: @5060668831052@(..1052)Dock & Bay Quick Dry Towel - Whi@1; | W60: N2 | AB60: 3.21 | AC60: 13.77 | AD60: 0.28
A61: 133400 | B61: AU-137030 | C61: 1 | D61: 3 | E61: 3 | F61: THURINGOWA CENTRAL | G61: 4817 | H61: AUSTRALIA | I61: 155 | J61: 0.473 | L61: 46140 | M61: @650966961381; | N61: Suburb Corrected. | O61: 1 | P61: 2 | Q61: 0 | R61: 0 | S61: @AXL6244807; | V61: @5061011626103@(..6103)Dock & Bay Tea Towel - Peas in a@1;@5061011625885@(..5885)Dock & Bay Tea Towel - Very Appe@1;@5061011625786@(..5786)Dock & Bay Tea Towel - Feelin' V@1; | W61: Q4 | AB61: 4.77 | AC61: 11.57 | AD61: 0.28
A62: 133401 | B62: AU-137031 | C62: 1 | D62: 3 | E62: 6 | F62: HILLARYS | G62: 6025 | H62: AUSTRALIA | I62: 155 | J62: 0.937 | L62: 46140 | M62: @650966961404; | O62: 1 | P62: 2 | Q62: 0 | R62: 0 | S62: @AXL6244787; | V62: @5061011628619@(..8619)Component Product@2;@5061011628626@(..8626)Component Product@2;@5061011628589@(..8589)Component Product@2; | W62: W0 | AB62: 6.18 | AC62: 12.93 | AD62: 0.28
A63: 133402 | B63: AU-137032 | C63: 1 | D63: 3 | E63: 3 | F63: EVERARD PARK | G63: 5035 | H63: AUSTRALIA | I63: 155 | J63: 1.683 | L63: 46140 | M63: @650966961404; | O63: 1 | P63: 2 | Q63: 0 | R63: 0 | S63: @AXL6284287; | V63: @5061011624413@(..4413)Dock & Bay Poncho - Adults - Uni@1;@5061011623669@(..3669)Dock & Bay Poncho - Adults - Coa@1;@5061011623706@(..3706)Dock & Bay Poncho - Adults - Yos@1; | W63: S0 | AB63: 4.77 | AC63: 9.86 | AD63: 0.28
A64: 133403 | B64: AU-137033 | C64: 1 | D64: 3 | E64: 6 | F64: MOONAH | G64: 7009 | H64: AUSTRALIA | I64: 155 | J64: 0.912 | L64: 46140 | M64: @650966961398; | N64: Suburb Corrected. | O64: 1 | P64: 2 | Q64: 0 | R64: 0 | S64: @AXL6244839; | V64: @5061011628619@(..8619)Component Product@2;@5061011628626@(..8626)Component Product@2;@5061011628589@(..8589)Component Product@2; | W64: T0 | AB64: 6.18 | AC64: 13.36 | AD64: 0.28
A65: 133404 | B65: AU-137034 | C65: 1 | D65: 4 | E65: 4 | F65: YANGEBUP | G65: 6164 | H65: AUSTRALIA | I65: 155 | J65: 2.044 | L65: 46140 | M65: @650966961404; | O65: 1 | P65: 2 | Q65: 0 | R65: 0 | S65: @AXL6284605; | V65: @5060668831137@(..1137)Component Product@1;@5060668831083@(..1083)Component Product@1;@5060668831120@(..1120)Component Product@1;@5060668833452@(..3452)Component Product@1; | W65: W0 | AB65: 5.55 | AC65: 17.69 | AD65: 0.28
A66: 133405 | B66: AU-137035 | C66: 1 | D66: 2 | E66: 2 | F66: MAROOCHYDORE | G66: 4558 | H66: AUSTRALIA | I66: 155 | J66: 0.748 | L66: 46140 | M66: @650966961398; | O66: 1 | P66: 2 | Q66: 0 | R66: 0 | S66: @AXL6139786; | V66: @5061011623218@(..3218)Dock & Bay Hair Wrap - Georgia P@1;@5061011628428@(..8428)Dock & Bay Quick Dry Bath Towel@1; | W66: SC | AB66: 3.99 | AC66: 12.74 | AD66: 0.28
A67: 133406 | B67: AU-137036 | C67: 1 | D67: 5 | E67: 5 | F67: RINGWOOD | G67: 3134 | H67: AUSTRALIA | I67: 155 | J67: 0.8 | L67: 46140 | M67: @650966961404; | O67: 1 | P67: 2 | Q67: 0 | R67: 0 | S67: @AXL6284360; | V67: @5061011625908@(..5908)Dock & Bay Tea Towel - Head Chef@1;@5061011628565@(..8565)Dock & Bay Tea Towel - Catch of@1;@5061011625779@(..5779)Dock & Bay Tea Towel - Cucumber@1;@5061011628589@(..8589)Dock & Bay Tea Towel - Kitchen D@1;@5061011625618@(..5618)Dock & Bay Tea Towel - Feeling S@1; | W67: V0 | AB67: 6.33 | AC67: 8.6 | AD67: 0.28
A68: 133407 | B68: AU-137037 | C68: 1 | D68: 1 | E68: 1 | F68: BRIGHTON EAST | G68: 3187 | H68: AUSTRALIA | I68: 155 | J68: 0.46 | L68: 46140 | M68: @650966961381; | O68: 1 | P68: 2 | Q68: 0 | R68: 0 | S68: @AXL6285093; | V68: @5060668830932@(..0932)Dock & Bay Quick Dry Towel - Bor@1; | W68: V0 | AB68: 3.21 | AC68: 6.93 | AD68: 0.28
A69: 133408 | B69: AU-137038 | C69: 1 | D69: 1 | E69: 2 | F69: PRAHRAN | G69: 3181 | H69: AUSTRALIA | I69: 155 | J69: 0.519 | L69: 46140 | M69: @650966961398; | O69: 1 | P69: 2 | Q69: 0 | R69: 0 | S69: @AXL6139810;@AXL6139810; | V69: @5061011628442@(..8442)Dock & Bay Hair Wrap - Cherry Bo@2; | W69: V0 | AB69: 3.68 | AC69: 8.6 | AD69: 0.28
A70: 133409 | B70: AU-137039 | C70: 1 | D70: 2 | E70: 2 | F70: MUIRHEAD | G70: 810 | H70: AUSTRALIA | I70: 155 | J70: 0.874 | L70: 46140 | M70: @650966961398; | O70: 1 | P70: 2 | Q70: 0 | R70: 0 | S70: @AXL6284515; | V70: @5060668830932@(..0932)Dock & Bay Quick Dry Towel - Bor@1;@5060668836224@(..6224)Dock & Bay Quick Dry Towel - Dee@1; | W70: NT1 | AB70: 3.99 | AC70: 23.64 | AD70: 0.28
A71: 133410 | B71: AU-137040 | C71: 1 | D71: 3 | E71: 3 | F71: CHINCHILLA | G71: 4413 | H71: AUSTRALIA | I71: 155 | J71: 1.022 | L71: 46140 | M71: @650966961398; | O71: 1 | P71: 2 | Q71: 0 | R71: 0 | S71: @AXL6284576; | V71: @5060668830918@(..0918)Dock & Bay Quick Dry Towel - Whi@1;@5061011623867@(..3867)Dock & Bay Small Waterproof Dry@1;@5060668833421@(..3421)Dock & Bay Quick Dry Towel - Cay@1; | W71: Q2 | AB71: 4.77 | AC71: 21.56 | AD71: 0.28
A72: 133411 | B72: AU-137041 | C72: 1 | D72: 1 | E72: 4 | F72: SOUTH GEELONG | G72: 3220 | H72: AUSTRALIA | I72: 155 | J72: 2.08 | L72: 46140 | M72: @650966961404; | O72: 1 | P72: 2 | Q72: 0 | R72: 0 | S72: @AXL6285223; | V72: @5060668831052@(..1052)Component Product@4; | W72: GL | AB72: 4.62 | AC72: 15.02 | AD72: 0.28
A73: 133412 | B73: AU-137042 | C73: 1 | D73: 2 | E73: 2 | F73: ATWELL | G73: 6164 | H73: AUSTRALIA | I73: 155 | J73: 0.87 | L73: 46140 | M73: @650966961398; | O73: 1 | P73: 2 | Q73: 0 | R73: 0 | S73: @AXL6269808; | V73: @5060668830987@(..0987)Dock & Bay Quick Dry Towel - Ipa@1;@5060668830994@(..0994)Dock & Bay Quick Dry Towel - Phi@1; | W73: W0 | AB73: 3.99 | AC73: 12.93 | AD73: 0.28
A74: 133413 | B74: AU-137043 | C74: 1 | D74: 5 | E74: 5 | F74: MORNINGSIDE | G74: 4170 | H74: AUSTRALIA | I74: 155 | J74: 0.775 | L74: 46140 | M74: @650966961398; | O74: 1 | P74: 2 | Q74: 0 | R74: 0 | S74: @AXL6244883; | V74: @5061011625830@(..5830)Component Product@1;@5061011628565@(..8565)Component Product@1;@5061011628589@(..8589)Component Product@1;@5061011628558@(..8558)Component Product@1;@5061011628572@(..8572)Component Product@1; | W74: Q0 | AB74: 6.33 | AC74: 8.6 | AD74: 0.28
A75: 133414 | B75: AU-137044 | C75: 1 | D75: 4 | E75: 4 | F75: WATERLOO | G75: 2017 | H75: AUSTRALIA | I75: 155 | J75: 2.06 | L75: 46140 | M75: @650966961404; | O75: 1 | P75: 2 | Q75: 0 | R75: 0 | S75: @AXL6285248; | V75: @5060668831069@(..1069)Component Product@1;@5060668831052@(..1052)Component Product@1;@5060668831045@(..1045)Component Product@1;@5060668833469@(..3469)Component Product@1; | W75: N0 | AB75: 5.55 | AC75: 6.01 | AD75: 0.28
A76: 133415 | B76: AU-137045 | C76: 1 | D76: 1 | E76: 1 | F76: REDAN | G76: 3350 | H76: AUSTRALIA | I76: 155 | J76: 0.464 | L76: 46140 | M76: @650966961381; | O76: 1 | P76: 2 | Q76: 0 | R76: 0 | S76: @AXL6284336; | V76: @5060668830925@(..0925)Dock & Bay Quick Dry Towel - Can@1; | W76: BR | AB76: 3.21 | AC76: 8.38 | AD76: 0.28
... A120: 133459 | B120: FBA15G940QS4 | C120: 1 | D120: 4 | E120: 80 | F120: KEMPS CREEK | G120: 2178 | H120: AUSTRALIA | I120: 55 | J120: 9.5 | L120: 46140 | M120: @32;@32; | O120: 1 | P120: 2 | Q120: 0 | R120: 0 | S120: @AXL6273920; | V120: @5061011628299@(..8299)Towels - Beach - Pastel Pier - G@20;@5061011624284@(..4284)Poncho - Adults - Malibu Pink -@10;@5061011625632@(..5632)Tea Towel - Check Please - GRS C@10;@5061011628565@(..8565)Tea Towel - Catch of the Day - G@40; | W120: N0 | AB120: 41.27 | AC120: 9.64 | AD120: 5.36
A121: 133459 | B121: FBA15G940QS4 | C121: 0 | D121: 0 | E121: 0 | F121: KEMPS CREEK | G121: 2178 | H121: AUSTRALIA | I121: 55 | J121: 15 | L121: 46140 | O121: 1 | S121: @AXL6273920; | W121: N0 | AB121: 0 | AC121: 9.91
A122: 133460 | B122: AU-137089 | C122: 1 | D122: 6 | E122: 6 | F122: FOREST LAKE | G122: 4078 | H122: AUSTRALIA | I122: 155 | J122: 2.4 | L122: 46140 | M122: @650966961404; | O122: 1 | P122: 2 | Q122: 0 | R122: 0 | S122: @AXL6269848; | V122: @5061011628312@(..8312)Component Product@1;@5061011628336@(..8336)Component Product@1;@5061011628343@(..8343)Component Product@1;@5061011628329@(..8329)Component Product@1;@5061011628565@(..8565)Dock & Bay Tea Towel - Catch of@1;@5061011625779@(..5779)Dock & Bay Tea Towel - Cucumber@1; | W122: Q0 | AB122: 7.11 | AC122: 9.97 | AD122: 0.28
A123: 133461 | B123: AU-137090 | C123: 1 | D123: 2 | E123: 2 | F123: MITCHAM | G123: 3132 | H123: AUSTRALIA | I123: 155 | J123: 1.06 | L123: 46140 | M123: @650966961398; | O123: 1 | P123: 2 | Q123: 0 | R123: 0 | S123: @AXL6269847; | V123: @5060668833452@(..3452)Dock & Bay Quick Dry Towel - Lom@1;@5060668833469@(..3469)Dock & Bay Quick Dry Towel - Cay@1; | W123: V0 | AB123: 3.99 | AC123: 9.27 | AD123: 0.28
A124: 133462 | B124: AU-137091 | C124: 1 | D124: 2 | E124: 2 | F124: EAST RYDE | G124: 2113 | H124: AUSTRALIA | I124: 155 | J124: 0.331 | L124: 46140 | M124: @650966961381; | O124: 1 | P124: 2 | Q124: 0 | R124: 0 | S124: @AXL6285814; | V124: @5061011623867@(..3867)Dock & Bay Small Waterproof Dry@1;@5060668837368@(..7368)Dock & Bay Foldaway Tote Bags -@1; | W124: N0 | AB124: 3.99 | AC124: 5.5 | AD124: 0.28
A125: 133463 | B125: 503-4029629-4523007 | C125: 1 | D125: 1 | E125: 1 | F125: SANDHURST | G125: 3977 | H125: AUSTRALIA | I125: 155 | J125: 0.206 | L125: 46140 | M125: @650966961381; | O125: 1 | P125: 2 | Q125: 0 | R125: 0 | S125: @AXL6281789; | V125: @5061011626134@(..6134)Dock & Bay Everyday Beach Tote B@1; | W125: V1 | AB125: 3.21 | AC125: 8.38 | AD125: 0.28
A126: 133464 | B126: AU-137092 | C126: 1 | D126: 3 | E126: 3 | F126: REDFERN | G126: 2016 | H126: AUSTRALIA | I126: 155 | J126: 0.926 | L126: 46140 | M126: @650966961404; | O126: 1 | P126: 2 | Q126: 0 | R126: 0 | S126: @AXL6281809; | V126: @5060668837351@(..7351)Dock & Bay Foldaway Tote Bags -@1;@5060668833407@(..3407)Dock & Bay Quick Dry Towel - Mal@1;@5060668835586@(..5586)Dock & Bay Quick Dry Towel - Mal@1; | W126: N0 | AB126: 4.77 | AC126: 5.96 | AD126: 0.28
A127: 133465 | B127: AU-137093 | C127: 1 | D127: 2 | E127: 2 | F127: MOONEE PONDS | G127: 3039 | H127: AUSTRALIA | I127: 154 | J127: 0.937 | L127: 46140 | M127: @650966961404; | O127: 1 | P127: 2 | Q127: 0 | R127: 0 | S127: @AXL6281790; | V127: @5061011623362@(..3362)Dock & Bay Quick Dry Towel - Coa@1;@5061011623508@(..3508)Dock & Bay Quick Dry Towel - Che@1; | W127: V0 | AB127: 3.99 | AC127: 13.11 | AD127: 0.28
A128: 133466 | B128: AU-137094 | C128: 1 | D128: 6 | E128: 8 | F128: TOOWOON BAY | G128: 2261 | H128: AUSTRALIA | I128: 154 | J128: 3.751 | L128: 46140 | M128: @6943389500751; | O128: 1 | P128: 2 | Q128: 0 | R128: 0 | S128: @AXL6281775; | V128: @5060668830918@(..0918)Dock & Bay Quick Dry Towel - Whi@1;@5061011623379@(..3379)Dock & Bay Quick Dry Towel - Mia@1;@5060668831052@(..1052)Dock & Bay Quick Dry Towel - Whi@1;@5061011623386@(..3386)Dock & Bay Quick Dry Towel - Coo@1;@5061011623447@(..3447)Dock & Bay Quick Dry Towel - Mia@2;@5061011623454@(..3454)Dock & Bay Quick Dry Towel - Coo@2; | W128: GF | AB128: 8.05 | AC128: 17.33 | AD128: 0.69
A129: 133467 | B129: AU-137095 | C129: 1 | D129: 4 | E129: 5 | F129: ANNANDALE | G129: 2038 | H129: AUSTRALIA | I129: 155 | J129: 1.892 | L129: 46141 | M129: @650966961398; | O129: 1 | P129: 2 | Q129: 0 | R129: 0 | S129: @AXL6288887; | V129: @5061011624215@(..4215)Dock & Bay Foldaway Tote Bags -@1;@5061011623362@(..3362)Dock & Bay Quick Dry Towel - Coa@1;@5061011627766@(..7766)Dock & Bay Quick Dry Towel - Fru@2;@5060668831335@(..1335)Dock & Bay Quick Dry Towel - Rai@1; | W129: N0 | AB129: 6.02 | AC129: 5.96 | AD129: 0.28
A130: 133468 | B130: AU-137096 | C130: 1 | D130: 1 | E130: 1 | F130: WARRANWOOD | G130: 3134 | H130: AUSTRALIA | I130: 155 | J130: 0.549 | L130: 46141 | M130: @650966961381; | O130: 1 | P130: 2 | Q130: 0 | R130: 0 | S130: @AXL6288764; | V130: @5061011621436@(..1436)Dock & Bay Quick Dry Towel - San@1; | W130: V0 | AB130: 3.21 | AC130: 8.6 | AD130: 0.28
A131: 133469 | B131: AU-137097 | C131: 1 | D131: 1 | E131: 1 | F131: REDFERN | G131: 2016 | H131: AUSTRALIA | I131: 155 | J131: 0.19 | L131: 46141 | M131: @650966961381; | O131: 1 | P131: 2 | Q131: 0 | R131: 0 | S131: @AXL6289890; | V131: @5061011625786@(..5786)Dock & Bay Tea Towel - Feelin' V@1; | W131: N0 | AB131: 3.21 | AC131: 5.5 | AD131: 0.28
A132: 133470 | B132: AU-137098 | C132: 1 | D132: 2 | E132: 2 | F132: BORONIA | G132: 3155 | H132: AUSTRALIA | I132: 155 | J132: 0.36 | L132: 46141 | M132: @650966961381; | O132: 1 | P132: 2 | Q132: 0 | R132: 0 | S132: @AXL6289862; | V132: @5061011625595@(..5595)Dock & Bay Hair Wrap - Wish You@1;@5061011628473@(..8473)Dock & Bay Hair Wrap - Pink Para@1; | W132: V0 | AB132: 3.99 | AC132: 6.93 | AD132: 0.28
A133: 133471 | B133: AU-137099 | C133: 1 | D133: 1 | E133: 1 | F133: NEWTOWN | G133: 2042 | H133: AUSTRALIA | I133: 155 | J133: 0.479 | L133: 46141 | M133: @650966961381; | O133: 1 | P133: 2 | Q133: 0 | R133: 0 | S133: @AXL6288794; | V133: @5061011623515@(..3515)Dock & Bay Quick Dry Towel - Gro@1; | W133: N0 | AB133: 3.21 | AC133: 5.5 | AD133: 0.28
... A193: 133531 | B193: AU-137159 | C193: 1 | D193: 1 | E193: 1 | F193: KINGSTON PARK | G193: 5049 | H193: AUSTRALIA | I193: 155 | J193: 0.448 | L193: 46143 | M193: @650966961381; | O193: 1 | P193: 2 | Q193: 0 | R193: 0 | S193: @AXL6296460; | V193: @5060668836224@(..6224)Dock & Bay Quick Dry Towel - Dee@1; | W193: S0 | AB193: 3.21 | AC193: 7.14 | AD193: 0.28

Sheet Other Requests
A1: Other Requests | F1: Quoted Rates : | G1: =SUMIF('Coghlan Settings'!J:J,"8.1",'Coghlan Settings'!M:M) -> 56.72 | H1: Warehouse Staff - Hourly Rate
A2: =Invoice!$G$3 & Invoice!$H$3 -> Inv # : DOK50347 | G2: =SUMIF('Coghlan Settings'!J:J,"8.2",'Coghlan Settings'!M:M) -> 56.72 | H2: Clerical Staff - Hourly Rate
A3: =Invoice!$G$4&TEXT(Invoice!$H$4,"dd mmm yy") -> Period End : 01 May 26 | G3: =SUMIF('Coghlan Settings'!J:J,"8.3",'Coghlan Settings'!M:M) -> 210.35 | H3: Software Development/IT - Hourly Rate
H4: Packaging Materials as Quoted
H5: Postage & Freight as Quoted
H6: Other adhoc Purchases as Quoted
M8: Total ($): | N8: =SUM(N11:N1048576) -> 1647.52
A10: ID | B10: TansactionType | C10: Date | D10: RequestedBy | E10: JobName | F10: JobReference | G10: Qty | H10: BillingNotes | I10: Charge Code | J10: ItemCode | K10: Description | L10: Item Qty | M10: Unit Price | N10: Total ($)
A13: DOK1015723 | C13: 46142 | D13: Nicole | E13: DOK133459 Special Instructions | F13: Amazon Kemps Creek | G13: 0 | I13: 8.2 | J13: LAB-A | K13: Admin Labour Hours | L13: 0.17 | M13: 56.72 | N13: 9.64
A14: DOK1015723 | I14: 8.1 | J14: LAB-W | K14: Warehouse Labour Hours | L14: 0.08 | M14: 56.72 | N14: 4.54
A16: DOKZ2544 | C16: 46143 | D16: Billing | E16: Storage | F16: WE 01-May-26 | G16: 0 | I16: 10.1 | J16: DOK--STR1 | K16: Storage per SKU on Hand | L16: 370 | M16: 0.36 | N16: 133.2
A17: DOKZ2544 | I17: 10.2 | J17: DOK--STR2 | K17: Storage per Unit of Stock on Hand | L17: 75007 | M17: 0.02 | N17: 1500.14

Sheet Packaging
A1: Packaging Materials
A2: =Invoice!$G$3 & Invoice!$H$3 -> Inv # : DOK50347
A3: =Invoice!$G$4&TEXT(Invoice!$H$4,"dd mmm yy") -> Period End : 01 May 26
A5: This is the full price list and provides you with an overview of packaging material consumption.
A6: Charges are applied at Order Level.
A8: Description | B8: Coghlan Stock | C8: Measurement | D8: Price | E8: Quantity
A10: Carton - 365 x 295 x 185 | B10: 14 | C10: 365 x 295 x 185 | D10: 1.04 | E10: 3
A11: Carton - 420 x 300 x 320 | B11: 16 | C11: 420 x 300 x 320 | D11: 1.43 | E11: 1
A12: Carton - 444 x 338 x 532 | B12: 32 | C12: 444 x 338 x 532 | D12: 2.68 | E12: 2
A13: Bubble Bag Size 5 | B13: 6943389500690 | C13: 241 x 345mm | D13: 0.61 | E13: 1
A14: Bubble Bag Size 6 | B14: 6943389500713 | C14: 304 x 400mm | D14: 0.81 | E14: 1
A15: Courier Tuff Bag Size 6 | B15: 6943389500751 | C15: 600 x 650mm | D15: 0.69 | E15: 1
A16: DOK Custom Medium Bag | B16: 650966961381 | C16: Per Bag | D16: 0.28 | E16: 81
A17: DOK Custom Large Bag | B17: 650966961398 | C17: Per Bag | D17: 0.28 | E17: 58
A18: DOK Custom XLarge Bag | B18: 650966961404 | C18: Per Bag | D18: 0.28 | E18: 33

Sheet Layout Summary
A1: Layout Summary
A2: =Invoice!$G$3 & Invoice!$H$3 -> Inv # : DOK50347
A3: =Invoice!$G$4&TEXT(Invoice!$H$4,"dd mmm yy") -> Period End : 01 May 26
A5: This list summarises your Order Processing costs by Layout Code. You can nominate which codes you would like to have listed.
A6: Contact accounts.receivable@coghlan.com.au. Information required: Layout Code & Description to appear here.
A7: Changes will apply to future invoices only. Please allow 2 business days to set up.
A8: There is no separate charge for this service.
A10: Layout Code | B10: Description | C10: Fulfilment Cost ($) | D10: Carrier Cost ($) | E10: Packaging Cost ($)
A12: Total | B12: (From Order Processing Page) | C12: =+'Order Processing'!AB9 -> 820.8 | D12: =+'Order Processing'!AC9 -> 1971.1 | E12: =+'Order Processing'!AD9 -> 60.18
A13: Others | B13: All other Layouts | C13: =C12-SUM('Layout Summary'!C14:C141) -> 820.8 | D13: =D12-SUM('Layout Summary'!D14:D141) -> 1971.1 | E13: =E12-SUM('Layout Summary'!E14:E141) -> 60.18
C14: =SUMIF('Order Processing'!$P:$P,$A14,'Order Processing'!AB:AB) -> 0 | D14: =SUMIF('Order Processing'!$P:$P,$A14,'Order Processing'!AC:AC) -> 0 | E14: =SUMIF('Order Processing'!$P:$P,$A14,'Order Processing'!AD:AD) -> 0
C15: =SUMIF('Order Processing'!$P:$P,$A15,'Order Processing'!AB:AB) -> 0 | D15: =SUMIF('Order Processing'!$P:$P,$A15,'Order Processing'!AC:AC) -> 0 | E15: =SUMIF('Order Processing'!$P:$P,$A15,'Order Processing'!AD:AD) -> 0
C16: =SUMIF('Order Processing'!$P:$P,$A16,'Order Processing'!AB:AB) -> 0 | D16: =SUMIF('Order Processing'!$P:$P,$A16,'Order Processing'!AC:AC) -> 0 | E16: =SUMIF('Order Processing'!$P:$P,$A16,'Order Processing'!AD:AD) -> 0
C17: =SUMIF('Order Processing'!$P:$P,$A17,'Order Processing'!AB:AB) -> 0 | D17: =SUMIF('Order Processing'!$P:$P,$A17,'Order Processing'!AC:AC) -> 0 | E17: =SUMIF('Order Processing'!$P:$P,$A17,'Order Processing'!AD:AD) -> 0
C18: =SUMIF('Order Processing'!$P:$P,$A18,'Order Processing'!AB:AB) -> 0 | D18: =SUMIF('Order Processing'!$P:$P,$A18,'Order Processing'!AC:AC) -> 0 | E18: =SUMIF('Order Processing'!$P:$P,$A18,'Order Processing'!AD:AD) -> 0
C19: =SUMIF('Order Processing'!$P:$P,$A19,'Order Processing'!AB:AB) -> 0 | D19: =SUMIF('Order Processing'!$P:$P,$A19,'Order Processing'!AC:AC) -> 0 | E19: =SUMIF('Order Processing'!$P:$P,$A19,'Order Processing'!AD:AD) -> 0
C20: =SUMIF('Order Processing'!$P:$P,$A20,'Order Processing'!AB:AB) -> 0 | D20: =SUMIF('Order Processing'!$P:$P,$A20,'Order Processing'!AC:AC) -> 0 | E20: =SUMIF('Order Processing'!$P:$P,$A20,'Order Processing'!AD:AD) -> 0
C21: =SUMIF('Order Processing'!$P:$P,$A21,'Order Processing'!AB:AB) -> 0 | D21: =SUMIF('Order Processing'!$P:$P,$A21,'Order Processing'!AC:AC) -> 0 | E21: =SUMIF('Order Processing'!$P:$P,$A21,'Order Processing'!AD:AD) -> 0
C22: =SUMIF('Order Processing'!$P:$P,$A22,'Order Processing'!AB:AB) -> 0 | D22: =SUMIF('Order Processing'!$P:$P,$A22,'Order Processing'!AC:AC) -> 0 | E22: =SUMIF('Order Processing'!$P:$P,$A22,'Order Processing'!AD:AD) -> 0
C23: =SUMIF('Order Processing'!$P:$P,$A23,'Order Processing'!AB:AB) -> 0 | D23: =SUMIF('Order Processing'!$P:$P,$A23,'Order Processing'!AC:AC) -> 0 | E23: =SUMIF('Order Processing'!$P:$P,$A23,'Order Processing'!AD:AD) -> 0
C24: =SUMIF('Order Processing'!$P:$P,$A24,'Order Processing'!AB:AB) -> 0 | D24: =SUMIF('Order Processing'!$P:$P,$A24,'Order Processing'!AC:AC) -> 0 | E24: =SUMIF('Order Processing'!$P:$P,$A24,'Order Processing'!AD:AD) -> 0
C25: =SUMIF('Order Processing'!$P:$P,$A25,'Order Processing'!AB:AB) -> 0 | D25: =SUMIF('Order Processing'!$P:$P,$A25,'Order Processing'!AC:AC) -> 0 | E25: =SUMIF('Order Processing'!$P:$P,$A25,'Order Processing'!AD:AD) -> 0
... C29: =SUMIF('Order Processing'!$P:$P,$A29,'Order Processing'!AB:AB) -> 0 | D29: =SUMIF('Order Processing'!$P:$P,$A29,'Order Processing'!AC:AC) -> 0 | E29: =SUMIF('Order Processing'!$P:$P,$A29,'Order Processing'!AD:AD) -> 0

Sheet Coghlan Settings
A1: Coghlan Settings
A2: =Invoice!$G$3 & Invoice!$H$3 -> Inv # : DOK50347
A3: =Invoice!$G$4&TEXT(Invoice!$H$4,"dd mmm yy") -> Period End : 01 May 26
A5: This Invoice:
A6: Date | B6: 46146
A7: Invoice Number | B7: DOK50347
A8: Effective Date | B8: 46143
B9: =IF(MONTH(B8)>=7,"WK"&(YEAR(B8)-2000)*100+ROUNDUP((B8+5-WEEKDAY(B8,2)-DATE(YEAR(B8),7,1))/7,0),"WK"&(YEAR(B8)-2000-1)*100+ROUNDUP((B8+5-WEEKDAY(B8,2)-DATE(YEAR(B8)-1,7,1))/7,0)) -> WK2544
A10: Storage | B10: =+SUM(Invoice!H12:H16) -> 0
A11: Operations | B11: =+B13-B10-B12 -> 2669.61
A12: Postage | B12: =Invoice!H20 -> 1971.1
A13: Total excl GST | B13: =Invoice!H27 -> 4640.71
A14: GST | B14: =Invoice!H28 -> 464.07
A15: Total incl GST | B15: =Invoice!H29 -> 5104.78
A25: From Customer File: | D25: From Site File: | G25: From Bank File: | J25: From Fulfillment Rate File:
A26: <Customer Code> | B26: DOK | D26: <Site> | E26: SYD | G26: <BankAccName> | H26: Coghlan Sydney Pty Ltd | J26: 1 | K26: Warehousing
A27: <Customer Name> | B27: Dock & Bay PTY LTD | D27: <CompanyName> | E27: Coghlan Sydney Pty Ltd | G27: <Bank> | H27: CBA | J27: 1.1 | K27: Per Pallet Stored (no cost for pallet hire) and / or | L27: Per Week | M27: 4.62
A28: <AttnName> | B28: Ben Muller | D28: <TradingName> | G28: <BSB> | H28: 062000 SWIFT: CTBAAU2S | J28: 1.2 | K28: Per In Pallet Racking Shelf | L28: Per Week | M28: 5.72
A29: <Address 1> | B29: PO Box 8006 | D29: <BusinessNumber1> | E29: ABN 53003527526 | G29: <AccountNumber> | H29: 21176183 | J29: 1.3 | K29: Per Small Item Shelf | L29: Per Week | M29: 3.53
A30: <Address 2> | D30: <Address1> | E30: PO Box 6890 | J30: 1.4 | K30: Per Small Item Shelf - 1/2 height | L30: Per Week | M30: 2.11
A31: <Suburb> | B31: Tumbi Umbi | D31: <Address2> | E31: Wetherill Park NSW 2164 | J31: 1.5 | K31: Small Item Tray | L31: Per Week | M31: 0.12
A32: <State> | B32: NSW | D32: <Address3> | E32: Australia | J32: 2 | K32: Goods into Store
A33: <Postcode> | B33: 2261 | D33: <GSTRate> | E33: 0.1 | J33: 2.1 | K33: Basic Charge then add | L33: Per Delivery | M33: 10.37
A34: <Country> | B34: Australia | J34: 2.2.1 | K34: Per Product Type Received then add | L34: Line/SKU | M34: 0
A35: <Email> | B35: ben@dockandbay.com | J35: 2.2.2 | K35: Per Item Received then add | L35: Per Item | M35: 0
A36: <Email2> | J36: 2.3 | K36: Per Standard Pallet (Single Product) or | L36: Per Pallet | M36: 9.75
A37: <Email3> | J37: 2.4 | K37: Per Carton (Single Product) or | L37: Per Carton | M37: 1.19
A38: <CPIDueDate> | B38: 46241 | J38: 2.5 | K38: Mixed or Unstructured Deliveries | L38: Per Man-Hour | M38: 56.72
A39: <PaymentTerms> | B39: Payment Terms: Strictly 7 Days Net | J39: 2.6
A40: <MYOBName> | B40: Dock & Bay PTY LTD | J40: 4 | K40: System
A41: <PackagingRateCard> | J41: 4.1 | K41: To Supply and Support System Including Standard Reporting | L41: Per Week | M41: 136.47
A42: <Factored> | B42: NOT FACTORED | J42: 5 | K42: Order Processing
A43: <Site> | B43: SYD | J43: 5.1 | K43: Price per Order Processed then add | L43: Per Order | M43: 2.43
A44: <BankAccount> | B44: SYD-Trading | J44: 5.2 | K44: Lines on Order then add | L44: Per Line | M44: 0.31
A45: <InvLayout> | J45: 5.3 | K45: Items on Order then add | L45: Per Item | M45: 0.47
A46: <LayoutSummaryTabReq> | B46: Y | J46: 5.4.1 | K46: Per Carton Despatched | L46: Per Carton | M46: 0
A47: <BillFrequency> | B47: WEEKLY | J47: 5.4.2 | K47: Per kilogram Despatched | L47: Per kg | M47: 0
A48: <SettlementDiscEnabled> | J48: 5.9 | K48: Packaging Materials (cost supplied separately)
A49: <SettlementDisc> | K49: Exceptions Processing
A50: <SettlementDiscNote> | J50: 5.5 | K50: Address Correction (when required) | L50: Per Order | M50: 0
A51: <RevenueSheet RegisterName> | B51: DOK - Dock & Bay PTY LTD | J51: 5.7 | K51: Despatch Communication - Email (optional) | L51: Per Order | M51: 0
A52: <BillingPrerequisite> | J52: 5.8 | K52: Despatch Communication - SMS (optional) | L52: Per Order | M52: 0
A53: <Discount1Volume> | J53: 6 | K53: Returns
A54: <Discount1Percent> | J54: 6.1 | K54: Returns Processing (basic) | L54: Per Return | M54: 4.64
A55: <Discount2Volume> | J55: 7 | K55: Carrier Options
A56: <Discount2Percent> | J56: 7.1 | K56: Refer Separate Sheet
A57: <Discount3Volume> | J57: 8 | K57: Hourly Charges (apply to other activities)
A58: <Discount3Percent> | J58: 8.1 | K58: Warehouse Staff | L58: Per Hour | M58: 56.72
A59: <Discount4Volume> | J59: 8.2 | K59: Clerical | L59: Per Hour | M59: 56.72
A60: <Discount4Percent> | J60: 8.3 | K60: Software Development/IT | L60: Per Hour | M60: 210.35
J61: 9 | K61: Database
J62: 9.1 | K62: Initial standard e-Quik set-up including Web Portal,FTP and Reports | L62: One-Time Fee
J63: 9.2 | K63: Per additional layout | L63: One-Time Fee | M63: 121.94
J64: 10 | K64: Special Charges
J65: 10.1 | K65: Storage per SKU on Hand | L65: Per SKU | M65: 0.36
J66: 10.2 | K66: Storage per Unit of Stock Held | L66: Per Unit | M66: 0.02
J67: 10.3 | K67: GRA Exception | L67: Per Exception | M67: 0
J68: 10.4 | M68: 0
J69: 10.5 | M69: 0
J70: 10.6 | M70: 0
J71: 10.7 | M71: 0
J72: 10.8 | M72: 0
J73: 10.9 | M73: 0
J74: 10.10 | K74: <Varies from customer to customer>
J75: 10.11 | K75: 40Ft Topper | L75: Per 40Ft Topper | M75: 0
J76: 10.12 | K76: 40Ft Container | L76: Per Other Container | M76: 0
J77: 10.13 | K77: 20Ft Container | L77: Per 20Ft Container | M77: 0
J78: 10.14 | K78: Outer Carton in Container | L78: Per Carton | M78: 0
J79: 10.15 | M79: 0
J80: 10.16 | M80: 0
J81: 10.17 | M81: 0
J82: 10.18 | M82: 0
J83: 10.19 | M83: 0
J84: 10.20 | K84: <Varies from customer to customer>
J85: 10.21 | M85: 0
J86: 10.22 | M86: 0
J87: 10.23 | M87: 0
J88: 10.24 | M88: 0
J89: 10.25 | M89: 0
J90: 10.26 | M90: 0
J91: 10.27 | M91: 0
J92: 10.28 | M92: 0
J93: 10.29 | M93: 0
J94: 10.30 | K94: <Varies from customer to customer>
J95: 10.31 | M95: 0
J96: 10.32 | M96: 0
J97: 10.33 | M97: 0
J98: 10.34 | M98: 0
J99: 10.35 | M99: 0
J100: 10.36 | M100: 0
J101: 10.37 | M101: 0
J102: 10.38 | M102: 0
J103: 10.39 | M103: 0
J104: 10.40 | K104: <Varies from customer to customer>
J105: 10.41 | M105: 0
J106: 10.42 | M106: 0
J107: 10.43 | M107: 0
J108: 10.44 | M108: 0
J109: 10.45 | M109: 0
J110: 10.46 | M110: 0
...
